dotlas/__init__.py
dotlas/app.py
dotlas/schemas/__init__.py
dotlas/schemas/cities.py
dotlas/schemas/competition.py
dotlas/schemas/sociodemographics.py
dotlas-1.0.3.dist-info/LICENSE
dotlas-1.0.3.dist-info/METADATA
dotlas-1.0.3.dist-info/WHEEL
dotlas-1.0.3.dist-info/top_level.txt
dotlas-1.0.3.dist-info/RECORD
