Metadata-Version: 2.1
Name: dotlas
Version: 1.0.3
Summary: Dotlas Python Package
Home-page: https://github.com/dotlas/api-client-python
Author: Dotlas Inc.
Author-email: tech@dotlas.com
License: UNKNOWN
Platform: UNKNOWN
Requires-Python: >=3.9
License-File: LICENSE
Requires-Dist: pydantic
Requires-Dist: requests
